{"cameraMode":{"drawMode":0,"name":"Shaded","section":"Shading Mode"},"sceneLighting":true,"audioPlay":false,"sceneViewState":{"m_AlwaysRefresh":false,"showFog":true,"showSkybox":true,"showFlares":true,"showImageEffects":true,"showParticleSystems":true,"showVisualEffectGraphs":true,"m_FxEnabled":true},"in2DMode":false,"pivot":{"x":2.7767558097839357,"y":9.103437423706055,"z":0.8932623863220215},"rotation":{"x":-0.009192943572998047,"y":-0.9606437087059021,"z":0.03200898692011833,"w":-0.2757977545261383},"size":1.6794579029083253,"orthographic":false}